{
  "name": "Blobcat",
  "type": "image",
  "items": [
    {
      "key": "blobcat 0_0",
      "val": "https://gcore.jsdelivr.net/gh/rt265/emoji@main/blobcat/0_0.gif"
    },
    {
      "key": "blobcat amused",
      "val": "https://gcore.jsdelivr.net/gh/rt265/emoji@main/blobcat/amused.gif"
    },
    {
      "key": "blobcat angel",
      "val": "https://gcore.jsdelivr.net/gh/rt265/emoji@main/blobcat/angel.gif"
    },
    {
      "key": "blobcat angery",
      "val": "https://gcore.jsdelivr.net/gh/rt265/emoji@main/blobcat/angery.gif"
    },
    {
      "key": "blobcat angry",
      "val": "https://gcore.jsdelivr.net/gh/rt265/emoji@main/blobcat/angry.gif"
    },
    {
      "key": "blobcat angry2",
      "val": "https://gcore.jsdelivr.net/gh/rt265/emoji@main/blobcat/angry2.gif"
    },
    {
      "key": "blobcat angrypuff",
      "val": "https://gcore.jsdelivr.net/gh/rt265/emoji@main/blobcat/angrypuff.gif"
    },
    {
      "key": "blobcat approach",
      "val": "https://gcore.jsdelivr.net/gh/rt265/emoji@main/blobcat/approach.gif"
    },
    {
      "key": "blobcat attention",
      "val": "https://gcore.jsdelivr.net/gh/rt265/emoji@main/blobcat/attention.gif"
    },
    {
      "key": "blobcat attentionrev",
      "val": "https://gcore.jsdelivr.net/gh/rt265/emoji@main/blobcat/attentionrev.gif"
    },
    {
      "key": "blobcat aww",
      "val": "https://gcore.jsdelivr.net/gh/rt265/emoji@main/blobcat/aww.gif"
    },
    {
      "key": "blobcat banhammerr",
      "val": "https://gcore.jsdelivr.net/gh/rt265/emoji@main/blobcat/banhammerr.gif"
    },
    {
      "key": "blobcat blush",
      "val": "https://gcore.jsdelivr.net/gh/rt265/emoji@main/blobcat/blush.gif"
    },
    {
      "key": "blobcat bongo",
      "val": "https://gcore.jsdelivr.net/gh/rt265/emoji@main/blobcat/bongo.gif"
    },
    {
      "key": "blobcat bongo1",
      "val": "https://gcore.jsdelivr.net/gh/rt265/emoji@main/blobcat/bongo1.gif"
    },
    {
      "key": "blobcat bongofaster",
      "val": "https://gcore.jsdelivr.net/gh/rt265/emoji@main/blobcat/bongofaster.gif"
    },
    {
      "key": "blobcat bongohyper",
      "val": "https://gcore.jsdelivr.net/gh/rt265/emoji@main/blobcat/bongohyper.gif"
    },
    {
      "key": "blobcat bop",
      "val": "https://gcore.jsdelivr.net/gh/rt265/emoji@main/blobcat/bop.gif"
    },
    {
      "key": "blobcat bounce",
      "val": "https://gcore.jsdelivr.net/gh/rt265/emoji@main/blobcat/bounce.gif"
    },
    {
      "key": "blobcat bouncefast",
      "val": "https://gcore.jsdelivr.net/gh/rt265/emoji@main/blobcat/bouncefast.gif"
    },
    {
      "key": "blobcat box",
      "val": "https://gcore.jsdelivr.net/gh/rt265/emoji@main/blobcat/box.gif"
    },
    {
      "key": "blobcat broken",
      "val": "https://gcore.jsdelivr.net/gh/rt265/emoji@main/blobcat/broken.gif"
    },
    {
      "key": "blobcat caged",
      "val": "https://gcore.jsdelivr.net/gh/rt265/emoji@main/blobcat/caged.gif"
    },
    {
      "key": "blobcat clipboard",
      "val": "https://gcore.jsdelivr.net/gh/rt265/emoji@main/blobcat/clipboard.gif"
    },
    {
      "key": "blobcat cmereyou",
      "val": "https://gcore.jsdelivr.net/gh/rt265/emoji@main/blobcat/cmereyou.gif"
    },
    {
      "key": "blobcat code",
      "val": "https://gcore.jsdelivr.net/gh/rt265/emoji@main/blobcat/code.gif"
    },
    {
      "key": "blobcat coffee",
      "val": "https://gcore.jsdelivr.net/gh/rt265/emoji@main/blobcat/coffee.gif"
    },
    {
      "key": "blobcat coffee2",
      "val": "https://gcore.jsdelivr.net/gh/rt265/emoji@main/blobcat/coffee2.gif"
    },
    {
      "key": "blobcat coffeespit",
      "val": "https://gcore.jsdelivr.net/gh/rt265/emoji@main/blobcat/coffeespit.gif"
    },
    {
      "key": "blobcat comftears",
      "val": "https://gcore.jsdelivr.net/gh/rt265/emoji@main/blobcat/comftears.gif"
    },
    {
      "key": "blobcat comfy",
      "val": "https://gcore.jsdelivr.net/gh/rt265/emoji@main/blobcat/comfy.gif"
    },
    {
      "key": "blobcat comfynight",
      "val": "https://gcore.jsdelivr.net/gh/rt265/emoji@main/blobcat/comfynight.gif"
    },
    {
      "key": "blobcat comfyslep",
      "val": "https://gcore.jsdelivr.net/gh/rt265/emoji@main/blobcat/comfyslep.gif"
    },
    {
      "key": "blobcat comfysweat",
      "val": "https://gcore.jsdelivr.net/gh/rt265/emoji@main/blobcat/comfysweat.gif"
    },
    {
      "key": "blobcat comfyuee",
      "val": "https://gcore.jsdelivr.net/gh/rt265/emoji@main/blobcat/comfyuee.gif"
    },
    {
      "key": "blobcat cool",
      "val": "https://gcore.jsdelivr.net/gh/rt265/emoji@main/blobcat/cool.gif"
    },
    {
      "key": "blobcat couple",
      "val": "https://gcore.jsdelivr.net/gh/rt265/emoji@main/blobcat/couple.gif"
    },
    {
      "key": "blobcat cozywave",
      "val": "https://gcore.jsdelivr.net/gh/rt265/emoji@main/blobcat/cozywave.gif"
    },
    {
      "key": "blobcat cry",
      "val": "https://gcore.jsdelivr.net/gh/rt265/emoji@main/blobcat/cry.gif"
    },
    {
      "key": "blobcat cyclone",
      "val": "https://gcore.jsdelivr.net/gh/rt265/emoji@main/blobcat/cyclone.gif"
    },
    {
      "key": "blobcat dab",
      "val": "https://gcore.jsdelivr.net/gh/rt265/emoji@main/blobcat/dab.gif"
    },
    {
      "key": "blobcat dancing",
      "val": "https://gcore.jsdelivr.net/gh/rt265/emoji@main/blobcat/dancing.gif"
    },
    {
      "key": "blobcat dead",
      "val": "https://gcore.jsdelivr.net/gh/rt265/emoji@main/blobcat/dead.gif"
    },
    {
      "key": "blobcat dealwithit",
      "val": "https://gcore.jsdelivr.net/gh/rt265/emoji@main/blobcat/dealwithit.gif"
    },
    {
      "key": "blobcat derp",
      "val": "https://gcore.jsdelivr.net/gh/rt265/emoji@main/blobcat/derp.gif"
    },
    {
      "key": "blobcat died",
      "val": "https://gcore.jsdelivr.net/gh/rt265/emoji@main/blobcat/died.gif"
    },
    {
      "key": "blobcat disturbed",
      "val": "https://gcore.jsdelivr.net/gh/rt265/emoji@main/blobcat/disturbed.gif"
    },
    {
      "key": "blobcat drool",
      "val": "https://gcore.jsdelivr.net/gh/rt265/emoji@main/blobcat/drool.gif"
    },
    {
      "key": "blobcat enjoy",
      "val": "https://gcore.jsdelivr.net/gh/rt265/emoji@main/blobcat/enjoy.gif"
    },
    {
      "key": "blobcat enjoyrain",
      "val": "https://gcore.jsdelivr.net/gh/rt265/emoji@main/blobcat/enjoyrain.gif"
    },
    {
      "key": "blobcat enjoysnow",
      "val": "https://gcore.jsdelivr.net/gh/rt265/emoji@main/blobcat/enjoysnow.gif"
    },
    {
      "key": "blobcat evil",
      "val": "https://gcore.jsdelivr.net/gh/rt265/emoji@main/blobcat/evil.gif"
    },
    {
      "key": "blobcat facepalm",
      "val": "https://gcore.jsdelivr.net/gh/rt265/emoji@main/blobcat/facepalm.gif"
    },
    {
      "key": "blobcat fearful",
      "val": "https://gcore.jsdelivr.net/gh/rt265/emoji@main/blobcat/fearful.gif"
    },
    {
      "key": "blobcat fingerguns",
      "val": "https://gcore.jsdelivr.net/gh/rt265/emoji@main/blobcat/fingerguns.gif"
    },
    {
      "key": "blobcat flip",
      "val": "https://gcore.jsdelivr.net/gh/rt265/emoji@main/blobcat/flip.gif"
    },
    {
      "key": "blobcat flower",
      "val": "https://gcore.jsdelivr.net/gh/rt265/emoji@main/blobcat/flower.gif"
    },
    {
      "key": "blobcat gay",
      "val": "https://gcore.jsdelivr.net/gh/rt265/emoji@main/blobcat/gay.gif"
    },
    {
      "key": "blobcat glare",
      "val": "https://gcore.jsdelivr.net/gh/rt265/emoji@main/blobcat/glare.gif"
    },
    {
      "key": "blobcat glarezoom",
      "val": "https://gcore.jsdelivr.net/gh/rt265/emoji@main/blobcat/glarezoom.gif"
    },
    {
      "key": "blobcat glassesdown",
      "val": "https://gcore.jsdelivr.net/gh/rt265/emoji@main/blobcat/glassesdown.gif"
    },
    {
      "key": "blobcat googlycry",
      "val": "https://gcore.jsdelivr.net/gh/rt265/emoji@main/blobcat/googlycry.gif"
    },
    {
      "key": "blobcat googlytrash",
      "val": "https://gcore.jsdelivr.net/gh/rt265/emoji@main/blobcat/googlytrash.gif"
    },
    {
      "key": "blobcat happypaws",
      "val": "https://gcore.jsdelivr.net/gh/rt265/emoji@main/blobcat/happypaws.gif"
    },
    {
      "key": "blobcat headphones",
      "val": "https://gcore.jsdelivr.net/gh/rt265/emoji@main/blobcat/headphones.gif"
    },
    {
      "key": "blobcat heart",
      "val": "https://gcore.jsdelivr.net/gh/rt265/emoji@main/blobcat/heart.gif"
    },
    {
      "key": "blobcat heartbreak",
      "val": "https://gcore.jsdelivr.net/gh/rt265/emoji@main/blobcat/heartbreak.gif"
    },
    {
      "key": "blobcat heartbroken",
      "val": "https://gcore.jsdelivr.net/gh/rt265/emoji@main/blobcat/heartbroken.gif"
    },
    {
      "key": "blobcat hearteyes",
      "val": "https://gcore.jsdelivr.net/gh/rt265/emoji@main/blobcat/hearteyes.gif"
    },
    {
      "key": "blobcat heartpride",
      "val": "https://gcore.jsdelivr.net/gh/rt265/emoji@main/blobcat/heartpride.gif"
    },
    {
      "key": "blobcat heartrainbow",
      "val": "https://gcore.jsdelivr.net/gh/rt265/emoji@main/blobcat/heartrainbow.gif"
    },
    {
      "key": "blobcat hero",
      "val": "https://gcore.jsdelivr.net/gh/rt265/emoji@main/blobcat/hero.gif"
    },
    {
      "key": "blobcat highfive",
      "val": "https://gcore.jsdelivr.net/gh/rt265/emoji@main/blobcat/highfive.gif"
    },
    {
      "key": "blobcat hissss",
      "val": "https://gcore.jsdelivr.net/gh/rt265/emoji@main/blobcat/hissss.gif"
    },
    {
      "key": "blobcat hug2",
      "val": "https://gcore.jsdelivr.net/gh/rt265/emoji@main/blobcat/hug2.gif"
    },
    {
      "key": "blobcat hungry",
      "val": "https://gcore.jsdelivr.net/gh/rt265/emoji@main/blobcat/hungry.gif"
    },
    {
      "key": "blobcat hyperthink",
      "val": "https://gcore.jsdelivr.net/gh/rt265/emoji@main/blobcat/hyperthink.gif"
    },
    {
      "key": "blobcat idea",
      "val": "https://gcore.jsdelivr.net/gh/rt265/emoji@main/blobcat/idea.gif"
    },
    {
      "key": "blobcat kissheart",
      "val": "https://gcore.jsdelivr.net/gh/rt265/emoji@main/blobcat/kissheart.gif"
    },
    {
      "key": "blobcat love",
      "val": "https://gcore.jsdelivr.net/gh/rt265/emoji@main/blobcat/love.gif"
    },
    {
      "key": "blobcat lurk",
      "val": "https://gcore.jsdelivr.net/gh/rt265/emoji@main/blobcat/lurk.gif"
    },
    {
      "key": "blobcat maracas",
      "val": "https://gcore.jsdelivr.net/gh/rt265/emoji@main/blobcat/maracas.gif"
    },
    {
      "key": "blobcat maracasfast",
      "val": "https://gcore.jsdelivr.net/gh/rt265/emoji@main/blobcat/maracasfast.gif"
    },
    {
      "key": "blobcat melt",
      "val": "https://gcore.jsdelivr.net/gh/rt265/emoji@main/blobcat/melt.gif"
    },
    {
      "key": "blobcat meltsob",
      "val": "https://gcore.jsdelivr.net/gh/rt265/emoji@main/blobcat/meltsob.gif"
    },
    {
      "key": "blobcat meltsoblove",
      "val": "https://gcore.jsdelivr.net/gh/rt265/emoji@main/blobcat/meltsoblove.gif"
    },
    {
      "key": "blobcat meltthumb",
      "val": "https://gcore.jsdelivr.net/gh/rt265/emoji@main/blobcat/meltthumb.gif"
    },
    {
      "key": "blobcat nervous",
      "val": "https://gcore.jsdelivr.net/gh/rt265/emoji@main/blobcat/nervous.gif"
    },
    {
      "key": "blobcat nervouspleading",
      "val": "https://gcore.jsdelivr.net/gh/rt265/emoji@main/blobcat/nervouspleading.gif"
    },
    {
      "key": "blobcat neutral",
      "val": "https://gcore.jsdelivr.net/gh/rt265/emoji@main/blobcat/neutral.gif"
    },
    {
      "key": "blobcat nod",
      "val": "https://gcore.jsdelivr.net/gh/rt265/emoji@main/blobcat/nod.gif"
    },
    {
      "key": "blobcat nodfast",
      "val": "https://gcore.jsdelivr.net/gh/rt265/emoji@main/blobcat/nodfast.gif"
    },
    {
      "key": "blobcat nogood",
      "val": "https://gcore.jsdelivr.net/gh/rt265/emoji@main/blobcat/nogood.gif"
    },
    {
      "key": "blobcat nom",
      "val": "https://gcore.jsdelivr.net/gh/rt265/emoji@main/blobcat/nom.gif"
    },
    {
      "key": "blobcat nomcookie",
      "val": "https://gcore.jsdelivr.net/gh/rt265/emoji@main/blobcat/nomcookie.gif"
    },
    {
      "key": "blobcat notif",
      "val": "https://gcore.jsdelivr.net/gh/rt265/emoji@main/blobcat/notif.gif"
    },
    {
      "key": "blobcat notlikethis",
      "val": "https://gcore.jsdelivr.net/gh/rt265/emoji@main/blobcat/notlikethis.gif"
    },
    {
      "key": "blobcat openmouth",
      "val": "https://gcore.jsdelivr.net/gh/rt265/emoji@main/blobcat/openmouth.gif"
    },
    {
      "key": "blobcat owo",
      "val": "https://gcore.jsdelivr.net/gh/rt265/emoji@main/blobcat/owo.gif"
    },
    {
      "key": "blobcat party",
      "val": "https://gcore.jsdelivr.net/gh/rt265/emoji@main/blobcat/party.gif"
    },
    {
      "key": "blobcat party2",
      "val": "https://gcore.jsdelivr.net/gh/rt265/emoji@main/blobcat/party2.gif"
    },
    {
      "key": "blobcat party2fast",
      "val": "https://gcore.jsdelivr.net/gh/rt265/emoji@main/blobcat/party2fast.gif"
    },
    {
      "key": "blobcat party2faster",
      "val": "https://gcore.jsdelivr.net/gh/rt265/emoji@main/blobcat/party2faster.gif"
    },
    {
      "key": "blobcat peek",
      "val": "https://gcore.jsdelivr.net/gh/rt265/emoji@main/blobcat/peek.gif"
    },
    {
      "key": "blobcat peek2",
      "val": "https://gcore.jsdelivr.net/gh/rt265/emoji@main/blobcat/peek2.gif"
    },
    {
      "key": "blobcat peekaboo",
      "val": "https://gcore.jsdelivr.net/gh/rt265/emoji@main/blobcat/peekaboo.gif"
    },
    {
      "key": "blobcat peekwave",
      "val": "https://gcore.jsdelivr.net/gh/rt265/emoji@main/blobcat/peekwave.gif"
    },
    {
      "key": "blobcat pensivepray",
      "val": "https://gcore.jsdelivr.net/gh/rt265/emoji@main/blobcat/pensivepray.gif"
    },
    {
      "key": "blobcat photo",
      "val": "https://gcore.jsdelivr.net/gh/rt265/emoji@main/blobcat/photo.gif"
    },
    {
      "key": "blobcat police",
      "val": "https://gcore.jsdelivr.net/gh/rt265/emoji@main/blobcat/police.gif"
    },
    {
      "key": "blobcat presentred",
      "val": "https://gcore.jsdelivr.net/gh/rt265/emoji@main/blobcat/presentred.gif"
    },
    {
      "key": "blobcat rave",
      "val": "https://gcore.jsdelivr.net/gh/rt265/emoji@main/blobcat/rave.gif"
    },
    {
      "key": "blobcat reach",
      "val": "https://gcore.jsdelivr.net/gh/rt265/emoji@main/blobcat/reach.gif"
    },
    {
      "key": "blobcat reachrev",
      "val": "https://gcore.jsdelivr.net/gh/rt265/emoji@main/blobcat/reachrev.gif"
    },
    {
      "key": "blobcat read",
      "val": "https://gcore.jsdelivr.net/gh/rt265/emoji@main/blobcat/read.gif"
    },
    {
      "key": "blobcat reeee",
      "val": "https://gcore.jsdelivr.net/gh/rt265/emoji@main/blobcat/reeee.gif"
    },
    {
      "key": "blobcat rollingeyes",
      "val": "https://gcore.jsdelivr.net/gh/rt265/emoji@main/blobcat/rollingeyes.gif"
    },
    {
      "key": "blobcat sad",
      "val": "https://gcore.jsdelivr.net/gh/rt265/emoji@main/blobcat/sad.gif"
    },
    {
      "key": "blobcat sadreach",
      "val": "https://gcore.jsdelivr.net/gh/rt265/emoji@main/blobcat/sadreach.gif"
    },
    {
      "key": "blobcat saitama",
      "val": "https://gcore.jsdelivr.net/gh/rt265/emoji@main/blobcat/saitama.gif"
    },
    {
      "key": "blobcat scared",
      "val": "https://gcore.jsdelivr.net/gh/rt265/emoji@main/blobcat/scared.gif"
    },
    {
      "key": "blobcat shocked",
      "val": "https://gcore.jsdelivr.net/gh/rt265/emoji@main/blobcat/shocked.gif"
    },
    {
      "key": "blobcat sip",
      "val": "https://gcore.jsdelivr.net/gh/rt265/emoji@main/blobcat/sip.gif"
    },
    {
      "key": "blobcat sippy",
      "val": "https://gcore.jsdelivr.net/gh/rt265/emoji@main/blobcat/sippy.gif"
    },
    {
      "key": "blobcat sipsweat",
      "val": "https://gcore.jsdelivr.net/gh/rt265/emoji@main/blobcat/sipsweat.gif"
    },
    {
      "key": "blobcat sipzoom",
      "val": "https://gcore.jsdelivr.net/gh/rt265/emoji@main/blobcat/sipzoom.gif"
    },
    {
      "key": "blobcat smiletear",
      "val": "https://gcore.jsdelivr.net/gh/rt265/emoji@main/blobcat/smiletear.gif"
    },
    {
      "key": "blobcat snapped",
      "val": "https://gcore.jsdelivr.net/gh/rt265/emoji@main/blobcat/snapped.gif"
    },
    {
      "key": "blobcat snuggle",
      "val": "https://gcore.jsdelivr.net/gh/rt265/emoji@main/blobcat/snuggle.gif"
    },
    {
      "key": "blobcat sob",
      "val": "https://gcore.jsdelivr.net/gh/rt265/emoji@main/blobcat/sob.gif"
    },
    {
      "key": "blobcat sobglasses",
      "val": "https://gcore.jsdelivr.net/gh/rt265/emoji@main/blobcat/sobglasses.gif"
    },
    {
      "key": "blobcat sparkle",
      "val": "https://gcore.jsdelivr.net/gh/rt265/emoji@main/blobcat/sparkle.gif"
    },
    {
      "key": "blobcat spin",
      "val": "https://gcore.jsdelivr.net/gh/rt265/emoji@main/blobcat/spin.gif"
    },
    {
      "key": "blobcat spinrainbow",
      "val": "https://gcore.jsdelivr.net/gh/rt265/emoji@main/blobcat/spinrainbow.gif"
    },
    {
      "key": "blobcat stretchy1",
      "val": "https://gcore.jsdelivr.net/gh/rt265/emoji@main/blobcat/stretchy1.gif"
    },
    {
      "key": "blobcat stretchy2",
      "val": "https://gcore.jsdelivr.net/gh/rt265/emoji@main/blobcat/stretchy2.gif"
    },
    {
      "key": "blobcat stretchy3",
      "val": "https://gcore.jsdelivr.net/gh/rt265/emoji@main/blobcat/stretchy3.gif"
    },
    {
      "key": "blobcat supersayin",
      "val": "https://gcore.jsdelivr.net/gh/rt265/emoji@main/blobcat/supersayin.gif"
    },
    {
      "key": "blobcat sweats",
      "val": "https://gcore.jsdelivr.net/gh/rt265/emoji@main/blobcat/sweats.gif"
    },
    {
      "key": "blobcat t",
      "val": "https://gcore.jsdelivr.net/gh/rt265/emoji@main/blobcat/t.gif"
    },
    {
      "key": "blobcat tap",
      "val": "https://gcore.jsdelivr.net/gh/rt265/emoji@main/blobcat/tap.gif"
    },
    {
      "key": "blobcat think",
      "val": "https://gcore.jsdelivr.net/gh/rt265/emoji@main/blobcat/think.gif"
    },
    {
      "key": "blobcat thinking",
      "val": "https://gcore.jsdelivr.net/gh/rt265/emoji@main/blobcat/thinking.gif"
    },
    {
      "key": "blobcat thinkingcool",
      "val": "https://gcore.jsdelivr.net/gh/rt265/emoji@main/blobcat/thinkingcool.gif"
    },
    {
      "key": "blobcat thinksmirk",
      "val": "https://gcore.jsdelivr.net/gh/rt265/emoji@main/blobcat/thinksmirk.gif"
    },
    {
      "key": "blobcat tired",
      "val": "https://gcore.jsdelivr.net/gh/rt265/emoji@main/blobcat/tired.gif"
    },
    {
      "key": "blobcat trampoline",
      "val": "https://gcore.jsdelivr.net/gh/rt265/emoji@main/blobcat/trampoline.gif"
    },
    {
      "key": "blobcat triumph",
      "val": "https://gcore.jsdelivr.net/gh/rt265/emoji@main/blobcat/triumph.gif"
    },
    {
      "key": "blobcat umm",
      "val": "https://gcore.jsdelivr.net/gh/rt265/emoji@main/blobcat/umm.gif"
    },
    {
      "key": "blobcat verified",
      "val": "https://gcore.jsdelivr.net/gh/rt265/emoji@main/blobcat/verified.gif"
    },
    {
      "key": "blobcat waitwhat",
      "val": "https://gcore.jsdelivr.net/gh/rt265/emoji@main/blobcat/waitwhat.gif"
    },
    {
      "key": "blobcat wave",
      "val": "https://gcore.jsdelivr.net/gh/rt265/emoji@main/blobcat/wave.gif"
    },
    {
      "key": "blobcat wavemelt",
      "val": "https://gcore.jsdelivr.net/gh/rt265/emoji@main/blobcat/wavemelt.gif"
    },
    {
      "key": "blobcat waverev",
      "val": "https://gcore.jsdelivr.net/gh/rt265/emoji@main/blobcat/waverev.gif"
    },
    {
      "key": "blobcat whaaaaat",
      "val": "https://gcore.jsdelivr.net/gh/rt265/emoji@main/blobcat/whaaaaat.gif"
    },
    {
      "key": "blobcat woah",
      "val": "https://gcore.jsdelivr.net/gh/rt265/emoji@main/blobcat/woah.gif"
    },
    {
      "key": "blobcat wobble",
      "val": "https://gcore.jsdelivr.net/gh/rt265/emoji@main/blobcat/wobble.gif"
    },
    {
      "key": "blobcat yandere",
      "val": "https://gcore.jsdelivr.net/gh/rt265/emoji@main/blobcat/yandere.gif"
    }
  ]
}
